[
    {
        "town_name": "г.Новосибирск"
    },
    {
        "entity_name": "МКП \"ГЭТ\" ГП"
    },
    {
        "entity_code": "ИНН 5402108170"
    },
    {
        "vehicle_type": "муниципальный / троллейбус"
    },
    {
        "route": "5"
    },
    {
        "trip": "16"
    },
    {
        "trip_date": "2021-08-15"
    },
    {
        "trip_time": "20:37:39"
    },
    {
        "terminal_id": "T020205"
    },
    {
        "ticket_serie": "0005404EED"
    },
    {
        "ticket_num": ""
    },
    {
        "transaction": ""
    },
    {
        "description": "",
        "value": ""
    },
    {
        "description": "",
        "value": ""
    }
]
